PyTuning-0.7.3.data/scripts/interactive.py
pytuning/__init__.py
pytuning/constants.py
pytuning/interactive.py
pytuning/metrics.py
pytuning/number_theory.py
pytuning/scale_creation.py
pytuning/utilities.py
pytuning/__pycache__/__init__.cpython-311.pyc
pytuning/__pycache__/constants.cpython-311.pyc
pytuning/__pycache__/interactive.cpython-311.pyc
pytuning/__pycache__/metrics.cpython-311.pyc
pytuning/__pycache__/number_theory.cpython-311.pyc
pytuning/__pycache__/scale_creation.cpython-311.pyc
pytuning/__pycache__/utilities.cpython-311.pyc
pytuning/scales/__init__.py
pytuning/scales/diatonic.py
pytuning/scales/edo.py
pytuning/scales/equal_interval.py
pytuning/scales/euler_fokker.py
pytuning/scales/harmonic.py
pytuning/scales/lucy.py
pytuning/scales/meantone.py
pytuning/scales/pythagorean.py
pytuning/scales/__pycache__/__init__.cpython-311.pyc
pytuning/scales/__pycache__/diatonic.cpython-311.pyc
pytuning/scales/__pycache__/edo.cpython-311.pyc
pytuning/scales/__pycache__/equal_interval.cpython-311.pyc
pytuning/scales/__pycache__/euler_fokker.cpython-311.pyc
pytuning/scales/__pycache__/harmonic.cpython-311.pyc
pytuning/scales/__pycache__/lucy.cpython-311.pyc
pytuning/scales/__pycache__/meantone.cpython-311.pyc
pytuning/scales/__pycache__/pythagorean.cpython-311.pyc
pytuning/tuning_tables/__init__.py
pytuning/tuning_tables/tuning_tables.py
pytuning/tuning_tables/__pycache__/__init__.cpython-311.pyc
pytuning/tuning_tables/__pycache__/tuning_tables.cpython-311.pyc
pytuning/visualizations/__init__.py
pytuning/visualizations/scales.py
pytuning/visualizations/syntonic.py
pytuning/visualizations/__pycache__/__init__.cpython-311.pyc
pytuning/visualizations/__pycache__/scales.cpython-311.pyc
pytuning/visualizations/__pycache__/syntonic.cpython-311.pyc
PyTuning-0.7.3.dist-info/METADATA
PyTuning-0.7.3.dist-info/WHEEL
PyTuning-0.7.3.dist-info/top_level.txt
PyTuning-0.7.3.dist-info/RECORD
