Metadata-Version: 2.1
Name: PyTuning
Version: 0.7.3
Summary: A Python package for the exploration of musical tunings.
Home-page: https://github.com/MarkCWirt/PyTuning
Author: Mark Conway Wirt
Author-email: markcwirt@gmail.com
License: MIT
Keywords: Music Scales Tuning Microtonalities
Platform: Platform Independent
Classifier: Development Status :: 4 - Beta
Classifier: Intended Audience :: Developers
Classifier: Intended Audience :: End Users/Desktop
Classifier: Programming Language :: Python :: 2.7
Classifier: Programming Language :: Python :: 3
Classifier: License :: OSI Approved :: MIT License
Classifier: Topic :: Multimedia :: Sound/Audio
Classifier: Topic :: Multimedia :: Sound/Audio :: Analysis
Classifier: Topic :: Software Development :: Libraries :: Python Modules
Requires-Dist: sympy
Requires-Dist: numpy
